pylibswathi/__init__.py
pylibswathi/core.py
pylibswathi-0.1.dist-info/licenses/LICENSE
pylibswathi-0.1.dist-info/METADATA
pylibswathi-0.1.dist-info/WHEEL
pylibswathi-0.1.dist-info/top_level.txt
pylibswathi-0.1.dist-info/RECORD
